homehubRPi/Listen.py
homehubRPi/UItoEdge_example.py
homehubRPi/__init__.py
homehubRPi/exampleMQTTclassUsage.py
homehubRPi/httpCommunications.py
homehubRPi/mqttCommunications.py
homehubRPi/mqtt_publish_example.py
homehubRPi/printme.py
homehubRPi-1.0.0.dist-info/LICENSE.txt
homehubRPi-1.0.0.dist-info/METADATA
homehubRPi-1.0.0.dist-info/WHEEL
homehubRPi-1.0.0.dist-info/top_level.txt
homehubRPi-1.0.0.dist-info/RECORD
