Metadata-Version: 2.1
Name: homehubRPi
Version: 1.0.0
Summary: A small home hub example package
Home-page: https://github.com/ngonimombeshora/homehubRPi
Author: Ngoni Mombeshora
Author-email: nmombeshora3@gmail.com
License: UNKNOWN
Download-URL: https://github.com/ngonimombeshora/homehubRPi/tree/main/dist/homehubRPi-1.0.0.tar.gz
Keywords: Smart home,IOT,Raspberry Pi,pip3,python,MQTT,HTTP/s,RESTful
Platform: UNKNOWN
Classifier: Intended Audience :: Developers
Classifier: Programming Language :: Python :: 3
Classifier: License :: OSI Approved :: MIT License
Classifier: Operating System :: OS Independent
Classifier: Topic :: System :: Operating System Kernels :: Linux
Requires-Python: >=3.6
